MANIFEST.in
README.rst
setup.py
esgprep/__init__.py
esgprep/esgcheckvocab.py
esgprep/esgdrs.py
esgprep/esgfetchini.py
esgprep/esgfetchtables.py
esgprep/esgmapfile.py
esgprep.egg-info/PKG-INFO
esgprep.egg-info/SOURCES.txt
esgprep.egg-info/dependency_links.txt
esgprep.egg-info/entry_points.txt
esgprep.egg-info/not-zip-safe
esgprep.egg-info/requires.txt
esgprep.egg-info/top_level.txt
esgprep/checkvocab/__init__.py
esgprep/checkvocab/constants.py
esgprep/checkvocab/context.py
esgprep/checkvocab/custom_exceptions.py
esgprep/checkvocab/main.py
esgprep/drs/__init__.py
esgprep/drs/constants.py
esgprep/drs/context.py
esgprep/drs/custom_exceptions.py
esgprep/drs/handler.py
esgprep/drs/main.py
esgprep/fetchini/__init__.py
esgprep/fetchini/constants.py
esgprep/fetchini/context.py
esgprep/fetchini/main.py
esgprep/fetchtables/__init__.py
esgprep/fetchtables/constants.py
esgprep/fetchtables/context.py
esgprep/fetchtables/main.py
esgprep/mapfile/__init__.py
esgprep/mapfile/constants.py
esgprep/mapfile/context.py
esgprep/mapfile/custom_exceptions.py
esgprep/mapfile/handler.py
esgprep/mapfile/main.py
esgprep/utils/__init__.py
esgprep/utils/collectors.py
esgprep/utils/constants.py
esgprep/utils/context.py
esgprep/utils/custom_exceptions.py
esgprep/utils/custom_print.py
esgprep/utils/github.py
esgprep/utils/help.py
esgprep/utils/misc.py
esgprep/utils/output_control.py
esgprep/utils/parser.py